LICENSE
MANIFEST.in
README.md
pyproject.toml
setup.py
src/nebulo/__init__.py
src/nebulo/cli.py
src/nebulo/config.py
src/nebulo/env.py
src/nebulo/exceptions.py
src/nebulo/lexer.py
src/nebulo.egg-info/PKG-INFO
src/nebulo.egg-info/SOURCES.txt
src/nebulo.egg-info/dependency_links.txt
src/nebulo.egg-info/entry_points.txt
src/nebulo.egg-info/requires.txt
src/nebulo.egg-info/top_level.txt
src/nebulo/gql/__init__.py
src/nebulo/gql/alias.py
src/nebulo/gql/parse_info.py
src/nebulo/gql/sqla_to_gql.py
src/nebulo/gql/convert/__init__.py
src/nebulo/gql/convert/column.py
src/nebulo/gql/convert/connection.py
src/nebulo/gql/convert/create.py
src/nebulo/gql/convert/delete.py
src/nebulo/gql/convert/function.py
src/nebulo/gql/convert/table.py
src/nebulo/gql/convert/update.py
src/nebulo/gql/relay/__init__.py
src/nebulo/gql/relay/cursor.py
src/nebulo/gql/relay/node_interface.py
src/nebulo/gql/relay/page_info.py
src/nebulo/gql/resolve/__init__.py
src/nebulo/gql/resolve/resolvers/__init__.py
src/nebulo/gql/resolve/resolvers/asynchronous.py
src/nebulo/gql/resolve/resolvers/claims.py
src/nebulo/gql/resolve/resolvers/default.py
src/nebulo/gql/resolve/transpile/__init__.py
src/nebulo/gql/resolve/transpile/mutation_builder.py
src/nebulo/gql/resolve/transpile/query_builder.py
src/nebulo/server/__init__.py
src/nebulo/server/app.py
src/nebulo/server/exception.py
src/nebulo/server/jwt.py
src/nebulo/server/starlette.py
src/nebulo/server/routes/__init__.py
src/nebulo/server/routes/graphiql.py
src/nebulo/server/routes/graphql.py
src/nebulo/sql/__init__.py
src/nebulo/sql/composite.py
src/nebulo/sql/inspect.py
src/nebulo/sql/statement_helpers.py
src/nebulo/sql/table_base.py
src/nebulo/sql/reflection/__init__.py
src/nebulo/sql/reflection/constraint_comments.py
src/nebulo/sql/reflection/function.py
src/nebulo/sql/reflection/manager.py
src/nebulo/sql/reflection/names.py
src/nebulo/sql/reflection/types.py
src/nebulo/sql/reflection/views.py
src/nebulo/static/graphiql.min.css
src/nebulo/static/graphiql.min.js
src/nebulo/text_utils/__init__.py
src/nebulo/text_utils/base64.py
src/nebulo/text_utils/casing.py
src/nebulo/text_utils/pluralize.py