Metadata-Version: 2.1
Name: nebulo
Version: 0.3.1
Summary: Nebulo: GraphQL API for PostgreSQL
Home-page: https://github.com/olirice/nebulo
Author: Oliver Rice
Author-email: oliver@oliverrice.com
License: MIT
Project-URL: Documentation, https://olirice.github.io/nebulo/
Project-URL: Source Code, https://github.com/olirice/nebulo
Keywords: graphql sqlalchemy sql api python
Platform: UNKNOWN
Classifier: Intended Audience :: Developers
Classifier: Programming Language :: Python :: 3.7
Classifier: Programming Language :: Python :: 3.8
Classifier: Programming Language :: Python :: 3.9
Requires-Python: >=3.7
Provides-Extra: test
Provides-Extra: nvim
Provides-Extra: dev
Provides-Extra: docs
